causal_world/__init__.py
causal_world/actors/__init__.py
causal_world/actors/base_policy.py
causal_world/actors/dummy_policy.py
causal_world/actors/grasping_policy.py
causal_world/actors/pick_and_place_policy.py
causal_world/actors/picking_policy.py
causal_world/actors/pushing_policy.py
causal_world/actors/random_policy.py
causal_world/actors/reacher_policy.py
causal_world/actors/stacking2_policy.py
causal_world/assets/baseline_actors/pick_and_place_ppo_curr0.zip
causal_world/assets/baseline_actors/picking_ppo_curr1.zip
causal_world/assets/baseline_actors/pushing_ppo_curr1.zip
causal_world/assets/baseline_actors/reaching_ppo_curr1.zip
causal_world/assets/baseline_actors/stacking2_ppo_curr1.zip
causal_world/assets/robot_properties_fingers/meshes/stl/trifinger_table_without_border.stl
causal_world/assets/robot_properties_fingers/meshes/stl/edu/base_back.stl
causal_world/assets/robot_properties_fingers/meshes/stl/edu/base_front.stl
causal_world/assets/robot_properties_fingers/meshes/stl/edu/base_side_left.stl
causal_world/assets/robot_properties_fingers/meshes/stl/edu/base_side_right.stl
causal_world/assets/robot_properties_fingers/meshes/stl/edu/base_top.stl
causal_world/assets/robot_properties_fingers/meshes/stl/edu/frame_wall.stl
causal_world/assets/robot_properties_fingers/meshes/stl/edu/lower_link.stl
causal_world/assets/robot_properties_fingers/meshes/stl/edu/middle_link.stl
causal_world/assets/robot_properties_fingers/meshes/stl/edu/upper_link.stl
causal_world/assets/robot_properties_fingers/urdf/trifinger.urdf
causal_world/assets/robot_properties_fingers/urdf/trifinger_edu.urdf
causal_world/benchmark/__init__.py
causal_world/benchmark/benchmarks.py
causal_world/configs/__init__.py
causal_world/configs/world_constants.py
causal_world/curriculum/__init__.py
causal_world/curriculum/curriculum.py
causal_world/dynamics_model/__init__.py
causal_world/dynamics_model/simulator_model.py
causal_world/envs/__init__.py
causal_world/envs/causalworld.py
causal_world-1.2.dist-info/LICENSE
causal_world-1.2.dist-info/METADATA
causal_world-1.2.dist-info/WHEEL
causal_world-1.2.dist-info/top_level.txt
causal_world-1.2.dist-info/RECORD
